simpleUID/__init__.py
simpleUID/exceptions.py
simpleUID/include.py
simpleUID/simpleUID.py
simpleUID-1.1.3.dist-info/LICENSE
simpleUID-1.1.3.dist-info/METADATA
simpleUID-1.1.3.dist-info/WHEEL
simpleUID-1.1.3.dist-info/top_level.txt
simpleUID-1.1.3.dist-info/RECORD
