Metadata-Version: 2.1
Name: simpleUID
Version: 1.1.3
Summary: A simple and intuitive Python package for generating unique IDs.
Home-page: https://github.com/w-kuipers/simpleUID
Author: Wibo Kuipers
Author-email: wkuipersoss@gmail.com
Project-URL: Bug Tracker, https://github.com/w-kuipers/simpleUID/issues
Classifier: Programming Language :: Python :: 3
Classifier: License :: OSI Approved :: MIT License
Classifier: Operating System :: OS Independent
Requires-Python: >=3.6
License-File: LICENSE
